fsbot/__init__.py
fsbot/fsbot.py
fsbot-0.1.6.dist-info/LICENSE
fsbot-0.1.6.dist-info/METADATA
fsbot-0.1.6.dist-info/WHEEL
fsbot-0.1.6.dist-info/top_level.txt
fsbot-0.1.6.dist-info/RECORD
