Metadata-Version: 2.1
Name: fsbot
Version: 0.1.6
Summary: fei shu notification
Home-page: https://github.com/zhaojunhang/feishu_notification.git
Author: zhaojunhang
Author-email: 454706391@qq.com
License: MIT Licence
Keywords: feishu
Platform: any
Requires-Dist: requests
Requires-Dist: urllib3
